pyape/__init__.py
pyape/__main__.py
pyape/cache.py
pyape/config.py
pyape/db.py
pyape/errors.py
pyape/flask_extend.py
pyape/flask_redis.py
pyape/logging.py
pyape/uwsgiproxy.py
pyape/uwsgitop.py
pyape/xmltodict.py
pyape/app/__init__.py
pyape/app/checker.py
pyape/app/queryfun.py
pyape/app/re2fun.py
pyape/app/rfun.py
pyape/app/vofun.py
pyape/app/models/__init__.py
pyape/app/models/regional.py
pyape/app/models/typeid.py
pyape/app/models/valueobject.py
pyape/builder/__init__.py
pyape/builder/command.py
pyape/builder/conf.py
pyape/builder/fabric.py
pyape/http/__init__.py
pyape/http/cdn.py
pyape/tpl/.gitignore
pyape/tpl/__init__.py
pyape/tpl/gunicorn.conf.py.jinja2
pyape/tpl/gunicorn_nginx.conf.jinja2
pyape/tpl/pyape.toml
pyape/tpl/supervisor_program.conf.jinja2
pyape/tpl/supervisord.conf.jinja2
pyape/tpl/supervisord.service.jinja2
pyape/tpl/uwsgi.ini.jinja2
pyape/tpl/wsgi.py
pyape/util/__init__.py
pyape/util/date.py
pyape/util/encrypt.py
pyape/util/func.py
pyape/util/gen.py
pyape-0.3.11.dist-info/LICENSE
pyape-0.3.11.dist-info/METADATA
pyape-0.3.11.dist-info/WHEEL
pyape-0.3.11.dist-info/entry_points.txt
pyape-0.3.11.dist-info/top_level.txt
pyape-0.3.11.dist-info/RECORD
