Metadata-Version: 2.1
Name: pyape
Version: 0.3.11
Summary: The Python Application Programming Environment.
Home-page: https://github.com/zrong/pyape
Author: zrong
Author-email: zrongzrong@gmail.com
License: BSD 3
Keywords: development zrong flask wechat
Platform: UNKNOWN
Classifier: Programming Language :: Python :: 3.9
Classifier: Development Status :: 4 - Beta
Classifier: Environment :: Console
Classifier: Environment :: Web Environment
Classifier: Operating System :: POSIX :: Linux
Classifier: Topic :: Internet :: WWW/HTTP :: Site Management
Classifier: Topic :: Utilities
Classifier: License :: OSI Approved :: BSD License
Requires-Python: >=3.9, <4
Requires-Dist: flask (>=2.0.2)
Requires-Dist: sqlalchemy (>=1.4.32)
Requires-Dist: fabric (>=2.7.0)
Requires-Dist: wheel
Requires-Dist: flask-compress
Requires-Dist: PyMySQL
Requires-Dist: python-dotenv
Requires-Dist: cryptography
Requires-Dist: redis
Requires-Dist: tomli
Requires-Dist: tomli-w
Requires-Dist: patchwork
Requires-Dist: python-json-logger
Requires-Dist: pyzmq
Requires-Dist: httpx
Requires-Dist: marshmallow
Requires-Dist: webargs
